mechanism_learn/__init__.py
mechanism_learn/gmmSampler.py
mechanism_learn/pipeline.py
mechanism_learn-2.3.1.dist-info/METADATA
mechanism_learn-2.3.1.dist-info/WHEEL
mechanism_learn-2.3.1.dist-info/top_level.txt
mechanism_learn-2.3.1.dist-info/RECORD
