Metadata-Version: 2.4
Name: mechanism-learn
Version: 2.3.1
Summary: Mechanism-learn is a simple method to deconfound observational data such that any appropriate machine learning model is forced to learn predictive relationships between effects and their causes, despite the potential presence of multiple unknown and unmeasured confounding. The library is compatible with most existing ML deployments. The library is compatible with most existing ML deployments such as models built with Scikit-learn and Keras.
Author-email: Jianqiao Mao <jxm1417@student.bham.ac.uk>
Project-URL: Homepage, https://github.com/JianqiaoMao/mechanism-learn
Requires-Python: >=3.9
Requires-Dist: causalBootstrapping>=0.2.0
Requires-Dist: grapl-causal
Requires-Dist: scipy
Requires-Dist: graphviz
Requires-Dist: tqdm
